<?xml version="1.0" encoding="iso-8859-1"?>
<mosinstall type="template">
  <name>hosting_01</name>
  <creationDate>March 2005</creationDate>
 <author>DesignForJoomla.com</author>
  <copyright>Converted to Joomla template by DesignForJoomla.com.</copyright>
  <authorEmail>design@designforjoomla.com</authorEmail>
  <authorUrl>www.designforjoomla.com</authorUrl>
  <version>1.0</version>
  <description>Converted to Joomla template by DesignForJoomla.com.</description>
  <files>
    <filename>index.php</filename>
    <filename>template_thumbnail.png</filename>
  </files>
  <images>
    
    <filename>images/demo1.gif</filename>
    <filename>images/demo2.gif</filename>
    <filename>images/gray_but_spacer.gif</filename>
    <filename>images/logo.gif</filename>
    <filename>images/orange_but_spacer.gif</filename>
    <filename>images/server.jpg</filename>
  </images>
  <css>
    <filename>css/template_css.css</filename>
  </css>
</mosinstall>
